cosette/__init__.py
cosette/_modidx.py
cosette/core.py
cosette/toolloop.py
cosette-0.2.5.dist-info/licenses/LICENSE
cosette-0.2.5.dist-info/METADATA
cosette-0.2.5.dist-info/WHEEL
cosette-0.2.5.dist-info/entry_points.txt
cosette-0.2.5.dist-info/top_level.txt
cosette-0.2.5.dist-info/RECORD
