Metadata-Version: 2.4
Name: cosette
Version: 0.2.5
Summary: A helper for using the OpenAI API
Home-page: https://github.com/AnswerDotAI/cosette
Author: Jeremy Howard
Author-email: j@fast.ai
License: Apache Software License 2.0
Keywords: nbdev jupyter notebook python
Classifier: Development Status :: 4 - Beta
Classifier: Intended Audience :: Developers
Classifier: Natural Language :: English
Classifier: Programming Language :: Python :: 3.9
Classifier: Programming Language :: Python :: 3.10
Classifier: License :: OSI Approved :: Apache Software License
Requires-Python: >=3.9
License-File: LICENSE
Requires-Dist: fastcore>=1.8.4
Requires-Dist: openai>=1.99.3
Requires-Dist: msglm>=0.0.8
Requires-Dist: toolslm>=0.3.0
Provides-Extra: dev
Requires-Dist: ipython; extra == "dev"
Dynamic: author
Dynamic: author-email
Dynamic: classifier
Dynamic: description
Dynamic: description-content-type
Dynamic: home-page
Dynamic: keywords
Dynamic: license
Dynamic: license-file
Dynamic: provides-extra
Dynamic: requires-dist
Dynamic: requires-python
Dynamic: summary
